pystyleclean/__init__.py
pystyleclean-1.0.dist-info/METADATA
pystyleclean-1.0.dist-info/WHEEL
pystyleclean-1.0.dist-info/top_level.txt
pystyleclean-1.0.dist-info/RECORD
